json_ext_encoder/__init__.py
json_ext_encoder/duration.py
json_ext_encoder/encoder.py
json_ext_encoder/timezone.py
json_ext_encoder-0.2.0.dist-info/LICENSE
json_ext_encoder-0.2.0.dist-info/WHEEL
json_ext_encoder-0.2.0.dist-info/METADATA
json_ext_encoder-0.2.0.dist-info/RECORD
