Metadata-Version: 2.1
Name: json-ext-encoder
Version: 0.2.0
Summary: Extended JSON encoder for Python data structures
Home-page: https://github.com/Gr1N/json-ext-encoder
License: MIT
Keywords: json,encoder,serialization
Author: Nikita Grishko
Author-email: gr1n@protonmail.com
Requires-Python: >=3.6,<4.0
Classifier: License :: OSI Approved :: MIT License
Classifier: Programming Language :: Python :: 3
Classifier: Programming Language :: Python :: 3.6
Classifier: Programming Language :: Python :: 3.7
Classifier: Topic :: Software Development :: Libraries :: Python Modules
